tridiax/__init__.py
tridiax/__version__.py
tridiax/divide_and_conquer.py
tridiax/stone.py
tridiax/thomas.py
tridiax-0.2.1.dist-info/LICENSE
tridiax-0.2.1.dist-info/METADATA
tridiax-0.2.1.dist-info/WHEEL
tridiax-0.2.1.dist-info/top_level.txt
tridiax-0.2.1.dist-info/RECORD
