Metadata-Version: 2.1
Name: tridiax
Version: 0.2.1
Summary: Solving tridiagonal systems.
Author-email: jaxleyverse <jaxleyverse@gmail.com>
Project-URL: source, https://github.com/jaxleyverse/tridiax
Project-URL: tracker, https://github.com/jaxleyverse/tridiax/issues
Keywords: tridiagonal,linear algebra,solver,jax
Classifier: Intended Audience :: Developers
Classifier: Intended Audience :: Education
Classifier: Intended Audience :: Science/Research
Classifier: Topic :: Adaptive Technologies
Classifier: Topic :: Scientific/Engineering
Classifier: Topic :: Scientific/Engineering :: Mathematics
Classifier: License :: OSI Approved :: Apache Software License
Classifier: Natural Language :: English
Classifier: Operating System :: OS Independent
Classifier: Programming Language :: Python :: 3
Classifier: Development Status :: 3 - Alpha
Requires-Python: >=3.8
License-File: LICENSE
Requires-Dist: jax
Requires-Dist: numpy
Provides-Extra: dev
Requires-Dist: black; extra == "dev"
Requires-Dist: isort; extra == "dev"
Requires-Dist: pytest; extra == "dev"
